drt_sdk_wallet/__init__.py
drt_sdk_wallet/constants.py
drt_sdk_wallet/core.py
drt_sdk_wallet/errors.py
drt_sdk_wallet/interfaces.py
drt_sdk_wallet/mnemonic.py
drt_sdk_wallet/mnemonic_test.py
drt_sdk_wallet/pem_entry.py
drt_sdk_wallet/pem_entry_test.py
drt_sdk_wallet/py.typed
drt_sdk_wallet/user_keys.py
drt_sdk_wallet/user_pem.py
drt_sdk_wallet/user_signer.py
drt_sdk_wallet/user_test.py
drt_sdk_wallet/user_verifer.py
drt_sdk_wallet/user_wallet.py
drt_sdk_wallet/validator_keys.py
drt_sdk_wallet/validator_pem.py
drt_sdk_wallet/validator_signer.py
drt_sdk_wallet/validator_test.py
drt_sdk_wallet/validator_verifier.py
drt_sdk_wallet/crypto/__init__.py
drt_sdk_wallet/crypto/constants.py
drt_sdk_wallet/crypto/decryptor.py
drt_sdk_wallet/crypto/encrypted_data.py
drt_sdk_wallet/crypto/encryptor.py
drt_sdk_wallet/crypto/randomness.py
drt_sdk_wallet/libraries/__init__.py
drt_sdk_wallet/libraries/bls_facade.py
drt_sdk_wallet/libraries/bls_facade_test.py
drt_sdk_wallet/libraries/libbls.dll
drt_sdk_wallet/libraries/libbls.dylib
drt_sdk_wallet/libraries/libbls.so
drt_sdk_wallet/libraries/libbls_arm64.dylib
drt_sdk_wallet-0.0.2.dist-info/METADATA
drt_sdk_wallet-0.0.2.dist-info/WHEEL
drt_sdk_wallet-0.0.2.dist-info/licenses/LICENSE
drt_sdk_wallet-0.0.2.dist-info/RECORD
