Metadata-Version: 2.3
Name: drt-sdk-wallet
Version: 0.0.2
Summary: Wallet & crypto components of Dharitri Python SDK.
Project-URL: Homepage, https://github.com/DharitriOne/drt-sdk-py-wallet
Author: Dharitri
License-Expression: MIT
License-File: LICENSE
Classifier: License :: OSI Approved :: MIT License
Classifier: Operating System :: OS Independent
Classifier: Programming Language :: Python :: 3
Requires-Python: >=3.8
Requires-Dist: cryptography==42.0.4
Requires-Dist: drt-sdk-core<0.1.0,>=0.0.1
Requires-Dist: mnemonic==0.20
Requires-Dist: pynacl==1.5.0
